cavalier/__init__.py
cavalier/logger.py
cavalier/metric.py
cavalier/datastore/__init__.py
cavalier/datastore/elasticsearch.py
cavalier-1.0.0.dist-info/LICENSE.txt
cavalier-1.0.0.dist-info/METADATA
cavalier-1.0.0.dist-info/WHEEL
cavalier-1.0.0.dist-info/top_level.txt
cavalier-1.0.0.dist-info/RECORD
