Metadata-Version: 2.1
Name: cavalier
Version: 1.0.0
Summary: Metrics Ingestion and Alerting Reimagined.
Home-page: https://github.com/uptimedog/cavalier/
Author: Clivern
Author-email: hello@clivern.com
License: MIT
Project-URL: Documentation, https://github.com/uptimedog/cavalier/
Project-URL: Source, https://github.com/uptimedog/cavalier/
Project-URL: Changelog, https://github.com/uptimedog/cavalier/blob/main/CHANGELOG.rst
Project-URL: Tracker, https://github.com/uptimedog/cavalier/issues
Project-URL: Download, https://pypi.org/project/cavalier/#files
Platform: any
Classifier: Development Status :: 5 - Production/Stable
Classifier: Programming Language :: Python
Classifier: License :: OSI Approved :: MIT License
License-File: LICENSE.txt
Requires-Dist: elasticsearch
Requires-Dist: importlib-metadata ; python_version < "3.8"
Provides-Extra: testing
Requires-Dist: elasticsearch ; extra == 'testing'
Requires-Dist: setuptools ; extra == 'testing'
Requires-Dist: pytest ; extra == 'testing'
Requires-Dist: pytest-cov ; extra == 'testing'
